rustc_dev_t_x64_win_msvc_nightly_p7/__init__.py
rustc_dev_t_x64_win_msvc_nightly_p7/data/darling_macro-4543ce35549bedf3.dll
rustc_dev_t_x64_win_msvc_nightly_p7/data/libannotate_snippets-3596be61cd3013c4.rmeta
rustc_dev_t_x64_win_msvc_nightly_p7/data/libar_archive_writer-bd3c7f43b8c57913.rmeta
rustc_dev_t_x64_win_msvc_nightly_p7/data/libbitflags-e73863e1568bf68a.rmeta
rustc_dev_t_x64_win_msvc_nightly_p7/data/libcfg_if-b737ddccf2d58419.rmeta
rustc_dev_t_x64_win_msvc_nightly_p7/data/libconstant_time_eq-427af6649bb922b9.rmeta
rustc_dev_t_x64_win_msvc_nightly_p7/data/libcrc32fast-6f3f542c853b42ca.rmeta
rustc_dev_t_x64_win_msvc_nightly_p7/data/libcrossbeam_deque-8d435cc19070e23a.rmeta
rustc_dev_t_x64_win_msvc_nightly_p7/data/libctrlc-9bd947ed363ba4a3.rmeta
rustc_dev_t_x64_win_msvc_nightly_p7/data/libeither-086ff17623818fc1.rmeta
rustc_dev_t_x64_win_msvc_nightly_p7/data/libelsa-4b8bd78ec003f651.rmeta
rustc_dev_t_x64_win_msvc_nightly_p7/data/libfluent_langneg-cd324e5d55d386cf.rmeta
rustc_dev_t_x64_win_msvc_nightly_p7/data/libgeneric_array-ca70cbc92cc451fc.rmeta
rustc_dev_t_x64_win_msvc_nightly_p7/data/libgetrandom-0bb07e032e2bfce5.rmeta
rustc_dev_t_x64_win_msvc_nightly_p7/data/libgetrandom-405d458b73a29dce.rmeta
rustc_dev_t_x64_win_msvc_nightly_p7/data/libhashbrown-7086d1c17e5a00e4.rmeta
rustc_dev_t_x64_win_msvc_nightly_p7/data/libicu_list_data-5bc3953a29400fb6.rmeta
rustc_dev_t_x64_win_msvc_nightly_p7/data/libicu_locid-fd2c18c7b2fecd9d.rmeta
rustc_dev_t_x64_win_msvc_nightly_p7/data/libicu_provider-029a459987b29d6c.rmeta
rustc_dev_t_x64_win_msvc_nightly_p7/data/libintl_pluralrules-0c0942612d0761a6.rmeta
rustc_dev_t_x64_win_msvc_nightly_p7/data/libitertools-59a717ae0162b9e2.rmeta
rustc_dev_t_x64_win_msvc_nightly_p7/data/libjobserver-22fbb380867a6eb9.rmeta
rustc_dev_t_x64_win_msvc_nightly_p7/data/libleb128-6375af0f5eb89639.rmeta
rustc_dev_t_x64_win_msvc_nightly_p7/data/liblibloading-6d712810001f8749.rmeta
rustc_dev_t_x64_win_msvc_nightly_p7/data/libmd5-932e814b88a3056a.rmeta
rustc_dev_t_x64_win_msvc_nightly_p7-1.91.0.dist-info/METADATA
rustc_dev_t_x64_win_msvc_nightly_p7-1.91.0.dist-info/WHEEL
rustc_dev_t_x64_win_msvc_nightly_p7-1.91.0.dist-info/top_level.txt
rustc_dev_t_x64_win_msvc_nightly_p7-1.91.0.dist-info/RECORD
